mostlyai/qa/__init__.py
mostlyai/qa/_accuracy.py
mostlyai/qa/_coherence.py
mostlyai/qa/_common.py
mostlyai/qa/_distances.py
mostlyai/qa/_embeddings.py
mostlyai/qa/_filesystem.py
mostlyai/qa/_html_report.py
mostlyai/qa/_sampling.py
mostlyai/qa/_similarity.py
mostlyai/qa/logging.py
mostlyai/qa/metrics.py
mostlyai/qa/random_state.py
mostlyai/qa/reporting.py
mostlyai/qa/reporting_from_statistics.py
mostlyai/qa/assets/__init__.py
mostlyai/qa/assets/embedders/potion-base-8M/README.md
mostlyai/qa/assets/embedders/potion-base-8M/config.json
mostlyai/qa/assets/embedders/potion-base-8M/model.safetensors
mostlyai/qa/assets/embedders/potion-base-8M/modules.json
mostlyai/qa/assets/embedders/potion-base-8M/tokenizer.json
mostlyai/qa/assets/html/bootstrap-5.3.3.bundle.min.js
mostlyai/qa/assets/html/bootstrap-5.3.3.min.css
mostlyai/qa/assets/html/explainer.svg
mostlyai/qa/assets/html/head.html
mostlyai/qa/assets/html/info.svg
mostlyai/qa/assets/html/plotly-3.0.1.min.js
mostlyai/qa/assets/html/report_early_exit.html
mostlyai/qa/assets/html/report_template.html
mostlyai/qa/assets/tokenizers/transformers/gpt2/merges.txt
mostlyai/qa/assets/tokenizers/transformers/gpt2/special_tokens_map.json
mostlyai/qa/assets/tokenizers/transformers/gpt2/tokenizer_config.json
mostlyai/qa/assets/tokenizers/transformers/gpt2/vocab.json
mostlyai_qa-1.9.9.dist-info/METADATA
mostlyai_qa-1.9.9.dist-info/WHEEL
mostlyai_qa-1.9.9.dist-info/licenses/LICENSE
mostlyai_qa-1.9.9.dist-info/RECORD
