Metadata-Version: 2.4
Name: mostlyai-qa
Version: 1.9.9
Summary: Synthetic Data Quality Assurance
Project-URL: homepage, https://github.com/mostly-ai/mostlyai-qa
Project-URL: repository, https://github.com/mostly-ai/mostlyai-qa
Project-URL: documentation, https://mostly-ai.github.io/mostlyai-qa/
Author-email: MOSTLY AI <dev@mostly.ai>
License-Expression: Apache-2.0
License-File: LICENSE
Classifier: Development Status :: 5 - Production/Stable
Classifier: Intended Audience :: Developers
Classifier: Intended Audience :: Financial and Insurance Industry
Classifier: Intended Audience :: Healthcare Industry
Classifier: Intended Audience :: Information Technology
Classifier: Intended Audience :: Science/Research
Classifier: Intended Audience :: Telecommunications Industry
Classifier: License :: OSI Approved :: Apache Software License
Classifier: Operating System :: OS Independent
Classifier: Programming Language :: Python :: 3.10
Classifier: Programming Language :: Python :: 3.11
Classifier: Programming Language :: Python :: 3.12
Classifier: Programming Language :: Python :: 3.13
Classifier: Topic :: Software Development :: Libraries
Classifier: Typing :: Typed
Requires-Python: >=3.10
Requires-Dist: accelerate>=1.5.0
Requires-Dist: jinja2>=3.1.5
Requires-Dist: joblib>=1.4.2
Requires-Dist: model2vec>=0.4.1
Requires-Dist: numpy>=1.26.3
Requires-Dist: pandas>=2.0.0
Requires-Dist: phik>=0.12.4
Requires-Dist: plotly>=6.0.0
Requires-Dist: pyarrow>=14.0.0
Requires-Dist: pydantic<3.0.0,>=2.0.0
Requires-Dist: scikit-learn>=1.4.0
Requires-Dist: scipy<1.16.0,>=1.11.0
Requires-Dist: torch>=2.6.0
Requires-Dist: transformers>=4.36.0
Requires-Dist: xxhash>=3.5.0
